delgado_logger/__init__.py
delgado_logger/logger.py
delgado_logger-1.2.1.dist-info/licenses/LICENSE
delgado_logger-1.2.1.dist-info/METADATA
delgado_logger-1.2.1.dist-info/WHEEL
delgado_logger-1.2.1.dist-info/top_level.txt
delgado_logger-1.2.1.dist-info/RECORD
