Metadata-Version: 2.4
Name: delgado_logger
Version: 1.2.1
Summary: A lightweight logging utility with value inspection and optional Black formatting.
Home-page: https://github.com/pyrometheous/Delgado-Logger
Author: Delgado
Author-email: Delgado <pyrometheous@gmail.com>
License: MIT
Classifier: Programming Language :: Python :: 3
Classifier: License :: OSI Approved :: MIT License
Classifier: Operating System :: OS Independent
Requires-Python: >=3.7
License-File: LICENSE
Requires-Dist: black>=24.0.0
Dynamic: author
Dynamic: home-page
Dynamic: license-file
Dynamic: requires-python
